pyggester/__init__.py
pyggester/cli.py
pyggester/command_handlers.py
pyggester/helpers.py
pyggester/main.py
pyggester/message_handler.py
pyggester/module_importer.py
pyggester/observable_collector.py
pyggester/observable_transformations.py
pyggester/observables.py
pyggester/pyggester.py
pyggester/text_formatters.py
pyggester/wrappers.py
pyggester/data/help_files/__init__.py
pyggester/data/help_files/dynamic_helper.md
pyggester/data/help_files/static_helper.md
pyggester-1.0.1.dist-info/LICENSE
pyggester-1.0.1.dist-info/METADATA
pyggester-1.0.1.dist-info/WHEEL
pyggester-1.0.1.dist-info/entry_points.txt
pyggester-1.0.1.dist-info/top_level.txt
pyggester-1.0.1.dist-info/RECORD
