Metadata-Version: 2.1
Name: pyggester
Version: 1.0.1
Summary: UNKNOWN
Home-page: UNKNOWN
Author: Valdon Vitija
Author-email: valdonvitijaa@gmail.com
License: MIT
Platform: UNKNOWN
License-File: LICENSE
Requires-Dist: Pygments ==2.17.2
Requires-Dist: astor ==0.8.1
Requires-Dist: click ==8.1.7
Requires-Dist: markdown-it-py ==3.0.0
Requires-Dist: mdurl ==0.1.2
Requires-Dist: numpy ==1.26.2
Requires-Dist: pandas ==2.1.4
Requires-Dist: python-dateutil ==2.8.2
Requires-Dist: pytz ==2023.3.post1
Requires-Dist: rich ==13.7.0
Requires-Dist: scipy ==1.11.4
Requires-Dist: six ==1.16.0
Requires-Dist: typer ==0.9.0
Requires-Dist: typing-extensions ==4.9.0
Requires-Dist: tzdata ==2023.3
